pizzoo/__init__.py
pizzoo/_constants.py
pizzoo/_renderers.py
pizzoo/_utils.py
pizzoo/default.bdf
pizzoo/game.py
pizzoo-0.9.14.dist-info/METADATA
pizzoo-0.9.14.dist-info/WHEEL
pizzoo-0.9.14.dist-info/top_level.txt
pizzoo-0.9.14.dist-info/RECORD
