Metadata-Version: 2.4
Name: pizzoo
Version: 0.9.14
Summary: Pizzoo is a easy-to-use library for rendering on pixel matrix screens like the Pixoo64, featuring easy new device integration, animation tools, and XML template rendering support.
Home-page: https://github.com/pabletos/pizzoo#readme
Author: Pablo Huet
License: MIT AND (Apache-2.0 OR BSD-2-Clause)
Keywords: pixoo,pixoo64,divoom,screen,pixel,matrix,render,buffer,LED matrix,LED,raspberry,raspberry pi
Classifier: Development Status :: 4 - Beta
Classifier: Topic :: Multimedia :: Graphics
Requires-Dist: requests>=2.31.0
Requires-Dist: Pillow>=11.1.0
Requires-Dist: bdfparser>=2.2.0
Dynamic: author
Dynamic: classifier
Dynamic: description
Dynamic: description-content-type
Dynamic: home-page
Dynamic: keywords
Dynamic: license
Dynamic: requires-dist
Dynamic: summary
